cat_year_calculator/__init__.py
cat_year_calculator/bin/__init__.py
cat_year_calculator/bin/cat_year_calc/__init__.py
cat_year_calculator/bin/cat_year_calc/arguments/__init__.py
cat_year_calculator/bin/cat_year_calc/arguments/errors.py
cat_year_calculator/bin/cat_year_calc/arguments/subcommands/__init__.py
cat_year_calculator/bin/cat_year_calc/arguments/subcommands/base_subcommand.py
cat_year_calculator/bin/cat_year_calc/arguments/subcommands/cat_to_human/__init__.py
cat_year_calculator/bin/cat_year_calc/arguments/subcommands/convert/__init__.py
cat_year_calculator/bin/cat_year_calc/arguments/subcommands/human_to_cat/__init__.py
cat_year_calculator/bin/cat_year_calc/arguments/subcommands/meta.py
cat_year_calculator/lib/__init__.py
cat_year_calculator/lib/common/__init__.py
cat_year_calculator/lib/common/errors.py
cat_year_calculator/lib/common/types.py
cat_year_calculator/lib/common/version/__init__.py
cat_year_calculator/lib/common/version/VERSION
cat_year_calculator/lib/converter.py
cat_year_calculator/lib/log_engine.py
cat_year_calculator-1.0.dev3.dist-info/entry_points.txt
cat_year_calculator-1.0.dev3.dist-info/LICENSE.md
cat_year_calculator-1.0.dev3.dist-info/METADATA
cat_year_calculator-1.0.dev3.dist-info/WHEEL
cat_year_calculator-1.0.dev3.dist-info/RECORD
